pyirt_sdt/PyIRT_SDT.py
pyirt_sdt/__init__.py
pyirt_sdt/pyirt-sdt.py
PyIRT_SDT-0.1.4.dist-info/METADATA
PyIRT_SDT-0.1.4.dist-info/WHEEL
PyIRT_SDT-0.1.4.dist-info/top_level.txt
PyIRT_SDT-0.1.4.dist-info/RECORD
