Metadata-Version: 2.1
Name: PyIRT_SDT
Version: 0.1.4
Summary: Python IRT calculator with SDT outputs, too, handling continuous and sparse data.
Home-page: https://github.com/omarclaflin/pyIRT_SDT
Author: Omar Claflin
Author-email: your.email@example.com
Classifier: Programming Language :: Python :: 3
Classifier: License :: OSI Approved :: MIT License
Classifier: Operating System :: OS Independent
Requires-Python: >=3.6
